<?xml version="1.0"?><mvc02.model.vo.Projeto>
  <prjCodigo>123</prjCodigo>
  <prjDescricao>Casa Azul</prjDescricao>
  <prjPlantaBaixa>
    <mvc02.model.vo.PlantaBaixa>
      <pbCodigo>101</pbCodigo>
      <pbSeqPiso>0</pbSeqPiso>
      <prjCodigo>123</prjCodigo>
      <pbPosX>0</pbPosX>
      <pbPosY>0</pbPosY>
      <pbPosZ>0</pbPosZ>
      <pbAreaPlantaBaixa>120</pbAreaPlantaBaixa>
      <pbPainel>
        <mvc02.model.vo.Painel>
          <pnCodigo>10</pnCodigo>
          <pnEspessura>5</pnEspessura>
          <pnAltura>3000</pnAltura>
          <pbCodigo>101</pbCodigo>
          <pnPos1>
            <X>0</X>
            <Y>0</Y>
          </pnPos1>
          <pnPos2>
            <X>5</X>
            <Y>0</Y>
          </pnPos2>
          <pnPos3>
            <X>5</X>
            <Y>1000</Y>
          </pnPos3>
          <pnPos4>
            <X>0</X>
            <Y>1000</Y>
          </pnPos4>
          <pnPerfil>
            <mvc02.model.vo.Perfil>
              <pfCodigo>100</pfCodigo>
              <pnCodigo>10</pnCodigo>
              <pfDesignacao>U</pfDesignacao>
              <pfOrientacao>90</pfOrientacao>
              <pfPosXIni>0</pfPosXIni>
              <pfPosYIni>0</pfPosYIni>
              <pfPosZIni>0</pfPosZIni>
              <pfAlma>90</pfAlma>
              <pfMesa>40</pfMesa>
              <pfEspessura>1</pfEspessura>
              <pfBorda>1</pfBorda>
              <pfDimensao>3000</pfDimensao>
              <pfDirecaoX>0.0</pfDirecaoX>
              <pfDirecaoY>0.0</pfDirecaoY>
            </mvc02.model.vo.Perfil>
            <mvc02.model.vo.Perfil>
              <pfCodigo>101</pfCodigo>
              <pnCodigo>10</pnCodigo>
              <pfDesignacao>U</pfDesignacao>
              <pfOrientacao>90</pfOrientacao>
              <pfPosXIni>300</pfPosXIni>
              <pfPosYIni>0</pfPosYIni>
              <pfPosZIni>0</pfPosZIni>
              <pfAlma>90</pfAlma>
              <pfMesa>40</pfMesa>
              <pfEspessura>1</pfEspessura>
              <pfBorda>1</pfBorda>
              <pfDimensao>3000</pfDimensao>
              <pfDirecaoX>0.0</pfDirecaoX>
              <pfDirecaoY>0.0</pfDirecaoY>
            </mvc02.model.vo.Perfil>
          </pnPerfil>
        </mvc02.model.vo.Painel>
        <mvc02.model.vo.Painel>
          <pnCodigo>11</pnCodigo>
          <pnEspessura>5</pnEspessura>
          <pnAltura>3000</pnAltura>
          <pbCodigo>101</pbCodigo>
          <pnPos1>
            <X>5</X>
            <Y>0</Y>
          </pnPos1>
          <pnPos2>
            <X>1005</X>
            <Y>0</Y>
          </pnPos2>
          <pnPos3>
            <X>1005</X>
            <Y>5</Y>
          </pnPos3>
          <pnPos4>
            <X>5</X>
            <Y>5</Y>
          </pnPos4>
        </mvc02.model.vo.Painel>
        <mvc02.model.vo.Painel>
          <pnCodigo>12</pnCodigo>
          <pnEspessura>5</pnEspessura>
          <pnAltura>3000</pnAltura>
          <pbCodigo>101</pbCodigo>
          <pnPos1>
            <X>1000</X>
            <Y>6</Y>
          </pnPos1>
          <pnPos2>
            <X>1005</X>
            <Y>6</Y>
          </pnPos2>
          <pnPos3>
            <X>1005</X>
            <Y>1000</Y>
          </pnPos3>
          <pnPos4>
            <X>1000</X>
            <Y>1000</Y>
          </pnPos4>
        </mvc02.model.vo.Painel>
        <mvc02.model.vo.Painel>
          <pnCodigo>13</pnCodigo>
          <pnEspessura>5</pnEspessura>
          <pnAltura>3000</pnAltura>
          <pbCodigo>101</pbCodigo>
          <pnPos1>
            <X>5</X>
            <Y>995</Y>
          </pnPos1>
          <pnPos2>
            <X>995</X>
            <Y>995</Y>
          </pnPos2>
          <pnPos3>
            <X>995</X>
            <Y>1000</Y>
          </pnPos3>
          <pnPos4>
            <X>5</X>
            <Y>1000</Y>
          </pnPos4>
        </mvc02.model.vo.Painel>
        <mvc02.model.vo.Painel>
          <pnCodigo>14</pnCodigo>
          <pnEspessura>5</pnEspessura>
          <pnAltura>3000</pnAltura>
          <pbCodigo>101</pbCodigo>
          <pnPos1>
            <X>500</X>
            <Y>5</Y>
          </pnPos1>
          <pnPos2>
            <X>505</X>
            <Y>5</Y>
          </pnPos2>
          <pnPos3>
            <X>505</X>
            <Y>705</Y>
          </pnPos3>
          <pnPos4>
            <X>500</X>
            <Y>705</Y>
          </pnPos4>
        </mvc02.model.vo.Painel>
        <mvc02.model.vo.Painel>
          <pnCodigo>15</pnCodigo>
          <pnEspessura>5</pnEspessura>
          <pnAltura>3000</pnAltura>
          <pbCodigo>101</pbCodigo>
          <pnPos1>
            <X>505</X>
            <Y>400</Y>
          </pnPos1>
          <pnPos2>
            <X>1000</X>
            <Y>400</Y>
          </pnPos2>
          <pnPos3>
            <X>1000</X>
            <Y>405</Y>
          </pnPos3>
          <pnPos4>
            <X>505</X>
            <Y>405</Y>
          </pnPos4>
        </mvc02.model.vo.Painel>
        <mvc02.model.vo.Painel>
          <pnCodigo>16</pnCodigo>
          <pnEspessura>5</pnEspessura>
          <pnAltura>3000</pnAltura>
          <pbCodigo>101</pbCodigo>
          <pnPos1>
            <X>500</X>
            <Y>705</Y>
          </pnPos1>
          <pnPos2>
            <X>1000</X>
            <Y>705</Y>
          </pnPos2>
          <pnPos3>
            <X>1000</X>
            <Y>710</Y>
          </pnPos3>
          <pnPos4>
            <X>500</X>
            <Y>710</Y>
          </pnPos4>
        </mvc02.model.vo.Painel>
        <mvc02.model.vo.Painel>
          <pnCodigo>17</pnCodigo>
          <pnEspessura>5</pnEspessura>
          <pnAltura>3000</pnAltura>
          <pbCodigo>101</pbCodigo>
          <pnPos1>
            <X>750</X>
            <Y>405</Y>
          </pnPos1>
          <pnPos2>
            <X>755</X>
            <Y>405</Y>
          </pnPos2>
          <pnPos3>
            <X>755</X>
            <Y>705</Y>
          </pnPos3>
          <pnPos4>
            <X>750</X>
            <Y>705</Y>
          </pnPos4>
        </mvc02.model.vo.Painel>
      </pbPainel>
    </mvc02.model.vo.PlantaBaixa>
  </prjPlantaBaixa>
</mvc02.model.vo.Projeto>